setup.py
cwcutils/__init__.py
cwcutils/clear.py
cwcutils.egg-info/PKG-INFO
cwcutils.egg-info/SOURCES.txt
cwcutils.egg-info/dependency_links.txt
cwcutils.egg-info/top_level.txt
cwcutils/dec/__init__.py
cwcutils/dec/coroutine.py
cwcutils/dec/group.py
cwcutils/dec/synchronized.py
cwcutils/dec/timeit.py