Metadata-Version: 1.0
Name: cwcutils
Version: 0.1.2
Summary: Useful functions over time
Home-page: UNKNOWN
Author: Chaowei Chen
Author-email: willhyper@gmail.com
License: MIT
Platform: UNKNOWN
